fleco/__init__.py
fleco-0.1.0.dist-info/LICENSE
fleco-0.1.0.dist-info/METADATA
fleco-0.1.0.dist-info/WHEEL
fleco-0.1.0.dist-info/top_level.txt
fleco-0.1.0.dist-info/RECORD
