Metadata-Version: 2.1
Name: fleco
Version: 0.1.0
Summary: An AI4S model toolkit
Home-page: https://github.com/lzxdn/fleco
Author: sugon-ai4s
Author-email: lidong6@sugon.com
Classifier: Programming Language :: Python :: 3
Classifier: License :: OSI Approved :: MIT License
Classifier: Operating System :: OS Independent
Requires-Python: >=3.8
License-File: LICENSE
Requires-Dist: numpy
